autodraft/__init__.py
autodraft/api.py
autodraft/arima.py
autodraft/gluonts.py
autodraft/visualization.py
autodraft-0.0.3.dist-info/LICENSE
autodraft-0.0.3.dist-info/METADATA
autodraft-0.0.3.dist-info/WHEEL
autodraft-0.0.3.dist-info/top_level.txt
autodraft-0.0.3.dist-info/RECORD
