Metadata-Version: 2.1
Name: autodraft
Version: 0.0.3
Summary: A small package for the AutoDraft streamlit app as well as working with the NHL's API.
Home-page: https://github.com/j4th/autodraft_pkg
Author: Justin Forth
Author-email: justinforth@gmail.com
License: UNKNOWN
Platform: UNKNOWN
Classifier: Programming Language :: Python :: 3
Classifier: License :: OSI Approved :: MIT License
Classifier: Operating System :: OS Independent
Requires-Python: >=3.6
